dcap_qvl_x86-0.0.1.dist-info/METADATA
dcap_qvl_x86-0.0.1.dist-info/WHEEL
dcap_qvl_x86-0.0.1.dist-info/licenses/LICENSE
dcap_qvl_x86/__init__.py
dcap_qvl_x86/dcap_qvl_x86.abi3.so
dcap_qvl_x86-0.0.1.dist-info/RECORD
