Metadata-Version: 2.4
Name: dcap-qvl-x86
Version: 0.0.1
Requires-Dist: maturin>=1.8.2
Requires-Dist: twine>=6.1.0
License-File: LICENSE
Summary: Add your description here
Author: Kevin Wang <wy721@qq.com>
Author-email: Kevin Wang <wy721@qq.com>
License: MIT
Requires-Python: >=3.10, <=3.14
